.coveragerc
.gitignore
.pre-commit-config.yaml
.travis.yml
LICENSE.txt
README.md
requirements.txt
setup.cfg
setup.py
tox.ini
docs/Makefile
docs/authors.rst
docs/changelog.rst
docs/conf.py
docs/index.rst
docs/license.rst
docs/_static/.gitignore
src/mlflowhelper/__init__.py
src/mlflowhelper.egg-info/PKG-INFO
src/mlflowhelper.egg-info/SOURCES.txt
src/mlflowhelper.egg-info/dependency_links.txt
src/mlflowhelper.egg-info/not-zip-safe
src/mlflowhelper.egg-info/requires.txt
src/mlflowhelper.egg-info/top_level.txt
src/mlflowhelper/tracking/__init__.py
src/mlflowhelper/tracking/artifactmanager.py
src/mlflowhelper/tracking/collections.py
src/mlflowhelper/tracking/fluent.py
src/mlflowhelper/tracking/nesting.py
tests/__init__.py
tests/conftest.py
tests/test_mlflowhelper.py
tests/travis_install.sh
tests/tracking/__init__.py
tests/tracking/test_collections.py