Metadata-Version: 2.1
Name: mlflowhelper
Version: 1.1.0
Summary: A set of tools for working with mlflow (see https://mlflow.org)
Home-page: https://github.com/mgbckr/mlflowhelper
Author: Martin Becker
Author-email: becker@informatik.uni-wuerzburg.de
License: mit
Project-URL: Documentation, https://github.com/mgbckr/mlflowhelper
Platform: any
Classifier: Programming Language :: Python
Requires-Python: >=3.4
Provides-Extra: testing
